uos_activpal/__init__.py
uos_activpal/gui/__init__.py
uos_activpal/gui/base.py
uos_activpal/gui/raw_marker.py
uos_activpal/gui/raw_viewer.py
uos_activpal/gui/resources/toolbar_bkground.png
uos_activpal/io/__init__.py
uos_activpal/io/raw.py
uos_activpal-0.2.2.dist-info/METADATA
uos_activpal-0.2.2.dist-info/RECORD
uos_activpal-0.2.2.dist-info/WHEEL
uos_activpal-0.2.2.dist-info/top_level.txt
