Metadata-Version: 2.1
Name: uos-activpal
Version: 0.2.2
Summary: A package for working with activPAL data
Home-page: https://github.com/R-Broadley/python-uos-activpal
Author: Rob Broadley
Author-email: software@rbroadley.co.uk
License: GPLv2
Download-URL: https://github.com/R-Broadley/python-uos-activpal/archive/0.2.2.tar.gz
Keywords: activpal,accelerometer,wearable,activity-monitor
Platform: UNKNOWN
Classifier: Programming Language :: Python :: 3
Classifier: License :: OSI Approved :: GNU General Public License v2 (GPLv2)
Classifier: Operating System :: OS Independent
Classifier: Development Status :: 4 - Beta
